<?xml version="1.0" encoding="UTF-8"?>
<!--
#~~~~~~~~~~~~~~~~~~~~~~~~~~~~~~~~~~~~~~~~~~~~~~~~~~~~~~~~~~~~~~~~~~~~~~~~~~~~~~~
# 
# $Id$
# 
# Copyright 2006 University of Dundee. All rights reserved.
# Use is subject to license terms supplied in LICENSE.txt
#
#~~~~~~~~~~~~~~~~~~~~~~~~~~~~~~~~~~~~~~~~~~~~~~~~~~~~~~~~~~~~~~~~~~~~~~~~~~~~~~~
-->
<types>
  <type id="ome.model.annotations.ImageAnnotation">
	  <properties>
		  <required name="image" type="ome.model.core.Image"/>
      <required name="content" type="text"/>      
	  </properties>
  </type>
  <type id="ome.model.annotations.DatasetAnnotation">
	  <properties>
		  <required name="dataset" type="ome.model.containers.Dataset"/>
      <required name="content" type="text"/>
	  </properties>
  </type>
</types>