<?xml version="1.0" encoding="UTF-8"?>
<!DOCTYPE beans PUBLIC "-//SPRING//DTD BEAN//EN" "http://www.springframework.org/dtd/spring-beans.dtd">
<!--
	#~~~~~~~~~~~~~~~~~~~~~~~~~~~~~~~~~~~~~~~~~~~~~~~~~~~~~~~~~~~~~~~~~~~~~~~~~~~~~~~
	# 
	# $Id: service-ome.api.ILdap.xml 1167 2007-06-04 10:39:34Z aleksandrat $
	# 
	# Copyright 2007 University of Dundee. All rights reserved.
	# Use is subject to license terms supplied in LICENSE.txt
	#
	#~~~~~~~~~~~~~~~~~~~~~~~~~~~~~~~~~~~~~~~~~~~~~~~~~~~~~~~~~~~~~~~~~~~~~~~~~~~~~~~
-->

<!--
	#~~~~~~~~~~~~~~~~~~~~~~~~~~~~~~~~~~~~~~~~~~~~~~~~~~~~~~~~~~~~~~~~~~~~~~~~~~~~~~~
	# Written by:  Aleksandra Tarkowska <aleksandrat@lifesci.dundee.ac.uk>
	#~~~~~~~~~~~~~~~~~~~~~~~~~~~~~~~~~~~~~~~~~~~~~~~~~~~~~~~~~~~~~~~~~~~~~~~~~~~~~~~
-->

<beans>

	<alias name="internal-ome.api.ILdap" alias="internal-ome.api.LocalLdap"/>

	<bean parent="level2" name="internal-ome.api.ILdap"
		class="ome.logic.LdapImpl">
		<description>
			Privileged bean which has several "private" references
			injected. This is not an example of what should be done.
		</description>
      <constructor-arg ref="simpleJdbcTemplate"/>
      <constructor-arg ref="ldapTemplate"/>
      <constructor-arg ref="roles"/>
      <constructor-arg ref="ldapConfig" />
	</bean>

	<bean name="managed-ome.api.ILdap" parent="managedService">
		<property name="proxyInterfaces">
			<list>
				<value>ome.api.ILdap</value>
			</list>
		</property>
		<property name="target" ref="internal-ome.api.ILdap" />
	</bean>


    <bean id="ldapConfig" class="ome.security.auth.LdapConfig">
      <constructor-arg index="0" value="${omero.ldap.config}"/>
      <constructor-arg index="1" value="${omero.ldap.new_user_group}"/>
      <constructor-arg index="2" value="${omero.ldap.groups}" />
      <constructor-arg index="3" value="${omero.ldap.attributes}" />
      <constructor-arg index="4" value="${omero.ldap.values}" />
      <constructor-arg index="5" value="${omero.ldap.user_filter}" />
      <constructor-arg index="6" value="${omero.ldap.group_filter}" />
      <constructor-arg index="7" value="${omero.ldap.user_mapping}" />
      <constructor-arg index="8" value="${omero.ldap.group_mapping}" />
    </bean>

	<bean id="ldapTemplate" class="org.springframework.ldap.core.LdapTemplate">
		<constructor-arg ref="contextSource" />
	</bean>

	<bean id="contextSource"
		class="ome.security.SecureLdapContextSource">
		<constructor-arg value="${omero.ldap.urls}"/>
		<property name="protocol" value="${omero.ldap.protocol}" />
		<property name="userDn" value="${omero.ldap.username}" />
		<property name="password" value="${omero.ldap.password}" />
		<property name="base" value="${omero.ldap.base}" />
		<property name="dirObjectFactory"
			value="org.springframework.ldap.core.support.DefaultDirObjectFactory" />
		<property name="keyStore" value="${omero.ldap.keyStore}" />
		<property name="keyStorePassword" value="${omero.ldap.keyStorePassword}" />
		<property name="trustStore" value="${omero.ldap.trustStore}" />
		<property name="trustStorePassword" value="${omero.ldap.trustStorePassword}" />
	</bean>

</beans>
